Predictive_smeters/__init__.py
Predictive_smeters/Config/__init__.py
Predictive_smeters/Config/config.py
Predictive_smeters/Config/settings/__init__.py
Predictive_smeters/Config/settings/Predictive_smeters_settings.py
Predictive_smeters/Config/settings/test_dataset_settings.py
Predictive_smeters/Config/test_data_dirs.py
Predictive_smeters/Config/test_data_files.py
Predictive_smeters/Models/__init__.py
Predictive_smeters/Models/elastic_net_regression.py
Predictive_smeters/RunModel/__init__.py
Predictive_smeters/RunModel/get_data.py
Predictive_smeters/RunModel/model.py
predictive_smeters-0.0.3.dist-info/License.txt
predictive_smeters-0.0.3.dist-info/METADATA
predictive_smeters-0.0.3.dist-info/WHEEL
predictive_smeters-0.0.3.dist-info/RECORD
