Metadata-Version: 2.1
Name: predictive-smeters
Version: 0.0.3
Summary: Package to implement a number of predictive models to predict energy consumption of households.
License: License.txt
Author: Jamie Corson
Author-email: jamie.corson.20@ucl.ac.uk
Requires-Python: ==3.8.5
Classifier: License :: Other/Proprietary License
Classifier: Programming Language :: Python :: 3
Requires-Dist: matplotlib (==3.7)
Requires-Dist: pandas (==2.0.3)
Requires-Dist: scikit-learn (>=1.3.1,<2.0.0)
